pyeisen/__init__.py
pyeisen/__main__.py
pyeisen/convolve.py
pyeisen/family.py
pyeisen/py.typed
pyeisen-0.1.1.dist-info/LICENSE
pyeisen-0.1.1.dist-info/METADATA
pyeisen-0.1.1.dist-info/WHEEL
pyeisen-0.1.1.dist-info/entry_points.txt
pyeisen-0.1.1.dist-info/RECORD
