Metadata-Version: 2.1
Name: pyeisen
Version: 0.1.1
Summary: PyEisen
Home-page: https://github.com/akhambhati/pyeisen
License: MIT
Author: Ankit Khambhati
Author-email: akhambhati@gmail.com
Requires-Python: >=3.11,<3.13
Classifier: Development Status :: 4 - Beta
Classifier: License :: OSI Approved :: MIT License
Classifier: Programming Language :: Python :: 3
Classifier: Programming Language :: Python :: 3.11
Requires-Dist: click (>=8.0.1)
Requires-Dist: numpy (>=1.25.2,<2.0.0)
Requires-Dist: pyfftw (>=0.13.1,<0.14.0)
Requires-Dist: scipy (>=1.11.2,<2.0.0)
Project-URL: Changelog, https://github.com/akhambhati/pyeisen/releases
Project-URL: Documentation, https://pyeisen.readthedocs.io
Project-URL: Repository, https://github.com/akhambhati/pyeisen
